{
  "type": "jra",
  "history": [
    {
      "date": "20260125",
      "by_place": {
        "小倉": {
          "invest": 3000,
          "payout": 0,
          "profit": -3000,
          "bet_races": 3,
          "hit": 0,
          "hit_rate": 0.0,
          "roi": 0.0
        },
        "京都": {
          "invest": 4000,
          "payout": 0,
          "profit": -4000,
          "bet_races": 4,
          "hit": 0,
          "hit_rate": 0.0,
          "roi": 0.0
        },
        "中山": {
          "invest": 4000,
          "payout": 0,
          "profit": -4000,
          "bet_races": 4,
          "hit": 0,
          "hit_rate": 0.0,
          "roi": 0.0
        }
      },
      "overall": {
        "invest": 11000,
        "payout": 0,
        "profit": -11000,
        "bet_races": 11,
        "hit": 0,
        "hit_rate": 0.0,
        "roi": 0.0,
        "pred_races": 0,
        "pred_hits": 0,
        "pred_hit_rate": 0.0
      },
      "pred_focus_races": 11,
      "pred_focus_by_place": {
        "中山": 4,
        "京都": 4,
        "小倉": 3
      },
      "pred_races": 0,
      "pred_hits": 0,
      "pred_hit_rate": 0.0,
      "pred_by_place": {
        "中山": {
          "races": 0,
          "hits": 0,
          "hit_rate": 0.0
        },
        "京都": {
          "races": 0,
          "hits": 0,
          "hit_rate": 0.0
        },
        "小倉": {
          "races": 0,
          "hits": 0,
          "hit_rate": 0.0
        }
      }
    }
  ],
  "total": {
    "invest": 11000,
    "payout": 0,
    "profit": -11000,
    "bet_races": 11,
    "hit": 0,
    "hit_rate": 0.0,
    "roi": 0.0,
    "pred_races": 0,
    "pred_hits": 0,
    "pred_hit_rate": 0.0
  },
  "by_place": {
    "中山": {
      "invest": 4000,
      "payout": 0,
      "profit": -4000,
      "bet_races": 4,
      "hit": 0,
      "pred_races": 0,
      "pred_hits": 0,
      "hit_rate": 0.0,
      "roi": 0.0,
      "pred_hit_rate": 0.0
    },
    "京都": {
      "invest": 4000,
      "payout": 0,
      "profit": -4000,
      "bet_races": 4,
      "hit": 0,
      "pred_races": 0,
      "pred_hits": 0,
      "hit_rate": 0.0,
      "roi": 0.0,
      "pred_hit_rate": 0.0
    },
    "小倉": {
      "invest": 3000,
      "payout": 0,
      "profit": -3000,
      "bet_races": 3,
      "hit": 0,
      "pred_races": 0,
      "pred_hits": 0,
      "hit_rate": 0.0,
      "roi": 0.0,
      "pred_hit_rate": 0.0
    }
  },
  "last_updated": "2026-02-08T15:28:15"
}